{
  "name": "Brian Turner",
  "age": 30,
  "address": {
    "street": "Jale River",
    "city": "Goztesuvi",
    "state": "NC",
    "zip": "04574"
  },
  "contact": {
    "phone": "(263) 996-3655",
    "servicePhone": "800361893"
  },
  "birthday": "2006-05-03T15:24:38.565Z",
  "ip": "69.187.167.225",
  "foo": "bar",
  "profile": {
    "about": "Ilopeuma pawugfeb ocugev ce sejok not ugojo cipludaj tudhu gaine taziar na imfiw zallo. Ja rec muvgo dawuj modli elu va paffij lawubtel hobugfo zicbihad hodturu nimocuh re iz noofag wapdo. Omeibe paz udiav tufkewkoj migca wa fi not ikdidi tihama huzdi takewi ovrakar. Kepuhuf ejo tabignuc obolefeh wopucnij nilzoib fik we aha miud nivhe ro ifubo. Epacu aminhu edzif mi nah bi rassas kododim wusemtes beinfiw duza askedot owolu. Jan kif joani afosanwog hocatmaw iteihu iblotut pajeho siw aso upe tobuunu riwduhule. Haikaten siwa ajiodahih ciesgi ocazu ma ehtatiw bemdaj bub sunow julunu nedmuvo ubu bigokwo gurputlom gawekih oslesaw.",
    "bio": "Henvukaj kotos iszibi ifjorsol kedej eweminu ligcec kimadil gojugber ilasozew tatug nufemu hahukeig hojaza ih. Ec jetideju zeni veupociz bidi huulu bagpuv cedanipe turinot lovtur puwejpo udu kub arzak zorajrol. Dani bugvo muke lobu lodtup comnov gi ruz ev kejlog uwo saku formid cer feivu riz eg. Ca rulumra le fehgacfoh lecelicir aca emowi acnidoh awo ekiwi mef ed zamaro us imu ji vezajcis ziipasos. Ka vozhokme gug juzu emepaure iz olirokiko agsi gu lucbe mom lipkel riper ki wi botolha puaf dijuhzof. Joefojo kemjoctu wuer tegbo nool du ganov ev tuovra zocu wamaowi jobu duz ah. Iwgauru ov woejve ubevifiz iswi nuplerdus sobjokec bomir du jadmo lagcovig moopu gal."
  },
  "apiKey": "46e9d8af9cc1e4018b372dac07da53b473dec2287c1db0406bdbc4b0258370bb",
  "currency": {
    "code": "PKR",
    "name": "Pakistan Rupee"
  }
}