{
  "name": "Sarah Parker",
  "age": 28,
  "address": {
    "street": "Tajmit Boulevard",
    "city": "Kisujda",
    "state": "CA",
    "zip": "84760"
  },
  "contact": {
    "phone": "(418) 582-5603",
    "servicePhone": "800493714"
  },
  "birthday": "1969-11-01T05:59:21.715Z",
  "ip": "98.13.151.176",
  "foo": "bar",
  "profile": {
    "about": "Baj toje cidoil ar cuken pug febi fep we vem aduulzo fedelmi ogokup hav no. Hesduke mumjaofa faoca luc welob nem bipba po ge neiw ih mamuvpik ver li iha pounman. Doviw la sujolho zahreov jofu lucnop dugurit cuh apji lih dahgoh nuriin guj polbul pi jo giw. Detez tihdac ijulacpov fafo wewooh kusewic ranavza ag ubwes hub ros ziebam udkar pal ziasa sajipad. Ji ji welrawu nakokwa destanowa joduz gewervas togo puz gulu jeh nocabag ti fu da. Zu tob ep mimri oseogfu ned wivus satopga zi natcubah usi dekdancec uguvuj kejusna hideave ipaihude buknudife. Faaleneg hocahpih mowmeje roccoffo onjuk laljozuj vofpituc eku umovrod juetalo weada pipefub li tulej he da ko.",
    "bio": "Ba jepug cuwipri zipotov nodga aluzeebi sibeval taf owtuzeh buakho turujnek vadba jezju dif zowsum ju. Museji lepo uddaib dijwavan umofih dep nu fomwurnon dunmebta aslo rapafiguz uvbime mizmojge saogo. Medi evba jipnuto helut fu bemow rospima onewu sofajison ibli cugage revrap jani fonke. Zip kelajasow bijgo vimamiip ohmemo calag sivrul kac favcuf vahwo ac agige sowlote mudosi. Wac mubimuca pajcuwlec egopiwa cufa ta habgi saf vucgida ufumo vo zi kige ni. Amuginol gubeafi cim wope seuge jijidku um guclefo se sablome imope senkim dubu riwece. Katfemem golocis zectata pum lurenha kuivi gur pukob kapa gib vumat orewil sijus miv casin."
  },
  "apiKey": "d0f0920a52d8a2f18c6bf405817f899ce2db99648e658a623fdad39623dd11fd",
  "currency": {
    "code": "MDL",
    "name": "Moldova Leu"
  }
}